pyatlas/__init__.py
pyatlas/atlas.py
pyatlas/atlas_entities.py
pyatlas/atlas_metadata.py
pyatlas/geometry.py
pyatlas/identifier_converters.py
pyatlas/pyatlas_globalfunc.py
pyatlas/spatial_index.py
pyatlas/autogen/Area_pb2.py
pyatlas/autogen/Edge_pb2.py
pyatlas/autogen/Line_pb2.py
pyatlas/autogen/Location_pb2.py
pyatlas/autogen/Node_pb2.py
pyatlas/autogen/Point_pb2.py
pyatlas/autogen/ProtoAtlasMetaData_pb2.py
pyatlas/autogen/ProtoAtlas_pb2.py
pyatlas/autogen/ProtoByteArrayOfArrays_pb2.py
pyatlas/autogen/ProtoByteArray_pb2.py
pyatlas/autogen/ProtoIntegerArrayOfArrays_pb2.py
pyatlas/autogen/ProtoIntegerArray_pb2.py
pyatlas/autogen/ProtoIntegerStringDictionary_pb2.py
pyatlas/autogen/ProtoLongArrayOfArrays_pb2.py
pyatlas/autogen/ProtoLongArray_pb2.py
pyatlas/autogen/ProtoLongToLongMap_pb2.py
pyatlas/autogen/ProtoLongToLongMultiMap_pb2.py
pyatlas/autogen/ProtoPackedTagStore_pb2.py
pyatlas/autogen/ProtoPolyLineArray_pb2.py
pyatlas/autogen/ProtoPolygonArray_pb2.py
pyatlas/autogen/Relation_pb2.py
pyatlas/autogen/Tag_pb2.py
pyatlas/autogen/__init__.py
pyatlas-5.8.9.dist-info/LICENSE
pyatlas-5.8.9.dist-info/METADATA
pyatlas-5.8.9.dist-info/WHEEL
pyatlas-5.8.9.dist-info/top_level.txt
pyatlas-5.8.9.dist-info/RECORD
