Metadata-Version: 2.1
Name: pyatlas
Version: 5.8.9
Summary: A simplified Python API for Atlas
Home-page: https://github.com/osmlab/atlas
Author: lucaspcram
Author-email: lucaspcram@gmail.com
License: BSD License
Platform: UNKNOWN
Classifier: Programming Language :: Python :: 3
Classifier: Operating System :: OS Independent
Classifier: License :: OSI Approved :: BSD License
